nbdev_test_2/__init__.py
nbdev_test_2/_modidx.py
nbdev_test_2/core.py
nbdev_test_2/test_2.py
nbdev_test_2-0.0.2.dist-info/LICENSE
nbdev_test_2-0.0.2.dist-info/METADATA
nbdev_test_2-0.0.2.dist-info/WHEEL
nbdev_test_2-0.0.2.dist-info/entry_points.txt
nbdev_test_2-0.0.2.dist-info/top_level.txt
nbdev_test_2-0.0.2.dist-info/RECORD
